LyingOn/BaseHandle.py
LyingOn/BasePage.py
LyingOn/__init__.py
LyingOn/__version__.py
LyingOn/logUtils.py
LyingOn/sendWechatMsg.py
lyingOn-0.1.3.dist-info/LICENSE
lyingOn-0.1.3.dist-info/METADATA
lyingOn-0.1.3.dist-info/WHEEL
lyingOn-0.1.3.dist-info/top_level.txt
lyingOn-0.1.3.dist-info/RECORD
