Metadata-Version: 2.1
Name: lyingOn
Version: 0.1.3
Summary: 躺着敲代码
Home-page: https://github.com/me/myproject
Author: chuqisky
Author-email: chuqisky@gmail.com
License: MIT
Platform: UNKNOWN
Classifier: License :: OSI Approved :: MIT License
Classifier: Programming Language :: Python
Classifier: Programming Language :: Python :: 3
Classifier: Programming Language :: Python :: 3.6
Classifier: Programming Language :: Python :: Implementation :: CPython
Classifier: Programming Language :: Python :: Implementation :: PyPy
Requires-Python: >=3.6.0
Requires-Dist: requests
Requires-Dist: selenium
Requires-Dist: urllib3
Requires-Dist: ddt
